portray/__init__.py
portray/__main__.py
portray/_version.py
portray/api.py
portray/cli.py
portray/config.py
portray/exceptions.py
portray/logo.py
portray/mkdocs_templates/partials/footer.html
portray/render.py
portray-1.7.0.dist-info/entry_points.txt
portray-1.7.0.dist-info/LICENSE
portray-1.7.0.dist-info/WHEEL
portray-1.7.0.dist-info/METADATA
portray-1.7.0.dist-info/RECORD
