Metadata-Version: 2.1
Name: portray
Version: 1.7.0
Summary: Your Project with Great Documentation
License: MIT
Author: Timothy Crosley
Author-email: timothy.crosley@gmail.com
Requires-Python: >=3.6,<4.0
Classifier: License :: OSI Approved :: MIT License
Classifier: Programming Language :: Python :: 3
Classifier: Programming Language :: Python :: 3.6
Classifier: Programming Language :: Python :: 3.7
Classifier: Programming Language :: Python :: 3.8
Classifier: Programming Language :: Python :: 3.9
Requires-Dist: GitPython (>=3.0,<4.0)
Requires-Dist: hug (>=2.6,<3.0)
Requires-Dist: livereload (>=2.6.3,<3.0.0)
Requires-Dist: mkdocs (>=1.2,<1.3)
Requires-Dist: mkdocs-material (>=7.0,<8.0)
Requires-Dist: pdocs (>=1.1.1,<2.0.0)
Requires-Dist: pymdown-extensions (>=7.0,<8.0)
Requires-Dist: toml (>=0.10.0,<0.11.0)
Requires-Dist: yaspin (>=0.15.0,<0.16.0)
